{"Summary":{"Canned":45677800,"allCount":928750893,"IssuredCount":946596797,"avlCount":317512,"productedCount":653324997.1666667},"CategoryColor":[{"label":"试机","color":"#2bbe17"},{"label":"酸酸乳","color":"#c6c10b"},{"label":"精选","color":"#38f6d1"},{"label":"宁夏夏进","color":"#f462cc"},{"label":"怡元康","color":"#ddc7cc"},{"label":"蒙牛白奶","color":"#f8bd74"},{"label":"三元儿童奶","color":"#cc3998"},{"label":"夏进塞上牧场纯牛奶","color":"#9aecdb"},{"label":"山西九牛纯牛奶","color":"#519715"},{"label":"山东牛太太中老年核桃牛奶","color":"#98f1a4"},{"label":"数码通测试","color":"#ac8eb0"},{"label":"河北初元_太子草莓果味饮品盒码_可变码","color":"#721b2e"},{"label":"宁夏夏进_益酸乳乳味饮料-红枣味_底标码","color":"#8a10ac"},{"label":"御膳香_顶羊纯山羊奶苗条_角标码","color":"#40d477"},{"label":"河北初元_太子无糖中老年果仁核桃牛奶盒码_可变码","color":"#5b13ad"},{"label":"纷美（北京）贸易_传统印刷流程测试","color":"#a88f7e"},{"label":"蒙牛未来星佳智型*迪士尼版*_可变码","color":"#599b06"},{"label":"重庆光大_重庆光大核桃花生奶_底标码","color":"#5667a6"},{"label":"河北初元_太子红枣果味饮品盒码_可变码","color":"#744dbc"},{"label":"天水华盛_珀菲科特核桃露_底标码","color":"#72e729"},{"label":"新希望蝶泉_新希望蝶泉红枣牛奶_角标码","color":"#57cce7"},{"label":"怡元康_福建达利园豆and豆豆奶马上白拿_可变码","color":"#5dbd7c"},{"label":"成都冠宇_桃源农庄高钙低脂中老年核桃牛奶_角标码","color":"#b39c0c"},{"label":"河北初元_太子红枣果味饮品盒码（201708宁夏太子）_可变码","color":"#dced0b"},{"label":"山东伊怡黑牛奶","color":"#3c9fb0"},{"label":"临沂格瑞_益膳房学生纯牛奶扫码学唐诗_可变图码","color":"#a0b3d0"},{"label":"成都冠宇_爱啡客椰子汁_可变码","color":"#9b999e"},{"label":"宝灌来太子奶核桃花生奶","color":"#3e8391"},{"label":"蒙牛_未来星成长牛奶*歌声的翅膀*-200S_可变码","color":"#9a9d28"},{"label":"纷美_测试MES","color":"#3e8ba1"},{"label":"福建杂粮世家_红豆浓浆_角标码","color":"#67b952"},{"label":"四川五谷源_卓旺高钙核桃花生早餐奶_角标码","color":"#7bf420"},{"label":"天水华盛_珀菲科特野生沙棘汁_底标码","color":"#80b707"},{"label":"重庆光大_重庆光大娟姗王纯牛奶_底标码","color":"#e201e9"},{"label":"四川菊乐_酸乐奶21周年纪念版_角标码","color":"#cd9c9f"},{"label":"怡元康_达利致醇新西兰牧场马上白拿_可变码","color":"#df0625"},{"label":"河北初元_太子草莓果味饮品盒码（201708宁夏太子）_可变码","color":"#7766f2"},{"label":"蒙牛未来星","color":"#f13dc0"},{"label":"成都冠宇爱啡客","color":"#f75576"},{"label":"四川奶小萌_伦苏牧场高钙核桃花生奶_角标码","color":"#e93a98"},{"label":"宝灌来太子奶中老年奶","color":"#484295"},{"label":"圣牧高科（天津）熔岩烧酸奶饮品_可变码","color":"#88c290"},{"label":"兔巴哥_核桃牛奶_角标码","color":"#2fcac5"},{"label":"新希望天香香蕉牛奶（酸奶杯系列）_可变图","color":"#e4e576"},{"label":"三元_倍固儿童成长牛奶（唐诗）_一包一码","color":"#4c6167"},{"label":"新希望阳平_新希望阳平核桃花生奶（新版）_角标码","color":"#954c16"},{"label":"重庆光大_重庆光大欧标牧场高钙低脂牛奶_底标码","color":"#e66856"},{"label":"成都冠宇桃源农庄高钙核桃花生奶苗条_角标码","color":"#10dd4a"},{"label":"纷美_测试印前协调999999","color":"#daec99"},{"label":"宝灌来_太子奶雪域风情耗牛慕斯蓝莓味乳味饮品_角标码","color":"#eb15b5"},{"label":"宁夏夏进_益酸乳乳味饮料-菠萝味_底标码","color":"#cd9660"},{"label":"怡元康_好彩头中老年高钙无蔗糖饮品_角标码","color":"#a5b63d"},{"label":"宝灌来_太子奶新西兰牧场奶_可变码","color":"#d68901"},{"label":"广美香满楼_麦香味早餐奶_角标码","color":"#66432a"},{"label":"宝灌来_太子奶中老年无蔗糖奶_可变码","color":"#48e444"},{"label":"福建杂粮世家_绿豆浓浆_角标码","color":"#f6c912"},{"label":"山东伊怡_甑酸奶芒果味盒码_可变码","color":"#46ac94"},{"label":"宝灌来_太子奶中老年牧场奶_可变码","color":"#a2b737"},{"label":"四川沁养_菲希塔希腊风味酸奶_可变码","color":"#bb05c0"},{"label":"河北初元_太子中老年果仁核桃牛奶盒码_可变码","color":"#5a2682"},{"label":"蒙牛_纯牛奶_港澳版*可变图码森林狼*","color":"#5536e7"},{"label":"蒙牛_未来星骨力型迪士尼版_可变码","color":"#8a25c0"},{"label":"新希望阳平_新希望阳平纯牛奶_角标码","color":"#9cd7ef"},{"label":"化州橘红_凉茶饮料_可变码","color":"#da7926"},{"label":"蒙牛_未来星佳智型迪士尼版_可变码","color":"#f6e810"},{"label":"四川奶小萌_豪旺高钙核桃花生奶_角标码","color":"#1bb120"},{"label":"福建杂粮世家_高钙核桃_角标码","color":"#6189e3"},{"label":"新希望雪兰_新希望雪兰好想好想原味乳味饮料_可变图","color":"#75ccb0"},{"label":"重庆光大_重庆光大皇冠纯牛奶_底标码","color":"#65dcd7"},{"label":"维维_天山雪艾小维醇乳酸青柠派_可变图码","color":"#462086"},{"label":"四川奶小萌_经旺高钙低糖核桃花生奶_角标码","color":"#a237f7"},{"label":"新希望蝶泉_新希望蝶泉原味乳酸菌饮品_角标码","color":"#3f34d7"},{"label":"新希望雪兰_新希望雪兰好想好想草莓味乳味饮料_可变图","color":"#a35be0"},{"label":"蒙牛_新养道零乳糖牛奶低脂型*改色电商版*_可变图","color":"#4ca86f"},{"label":"宝灌来_太子奶核桃花生奶标砖_可变码","color":"#e3f73e"},{"label":"新希望天香_新希望天香香蕉牛奶_可变图码","color":"#adb9a3"},{"label":"可变印刷_可变印刷测试","color":"#ece376"},{"label":"成都冠宇_卓旺高钙核桃奶_角标码","color":"#ab6480"},{"label":"四川元明_鑫元明草莓味酸乐奶_角标码","color":"#b68612"},{"label":"新希望天香_新希望天香香蕉牛奶熊猫TV混印_可变码","color":"#ef2e15"},{"label":"圣牧高科（天津）_熔岩烧酸奶饮品*改配料版*_可变码","color":"#ce2730"},{"label":"兔巴哥_兔巴哥山楂汁盒码_可变码","color":"#e2b850"},{"label":"测试白包_GAB250S隐藏折角码","color":"#c437a8"},{"label":"新希望雪兰_新希望雪兰骨优型儿童成长牛奶_可变图码","color":"#8ace99"},{"label":"成都冠宇_蓉城家人高钙核桃奶苗条_角标码","color":"#492dd0"},{"label":"新希望雪兰_新希望雪兰易聪型儿童成长牛奶_可变图码","color":"#4d67d5"},{"label":"四川奶小萌_经旺高钙核桃花生奶_角标码","color":"#12506a"},{"label":"四川草本_牧优高钙核桃花生牛奶_角标码","color":"#4b8143"},{"label":"蒙牛_新养道零乳糖牛奶低脂型*电商版*_可变图","color":"#fc4219"},{"label":"成都冠宇_蜀罐黑芝麻珍品花生奶_角标码","color":"#6630ea"},{"label":"汇源禹城_汇源绿动绿豆饮料_角标码","color":"#92294a"},{"label":"新希望琴牌_新希望琴牌致轻低脂纯牛奶文字可变_可变图","color":"#9dccf0"},{"label":"兔巴哥_花生牛奶_角标码","color":"#28b496"},{"label":"完达慕容高钙核桃牛奶_角标码","color":"#dc7764"},{"label":"云南乍甸_云南乍甸纯牛奶_角标码","color":"#4e8dff"},{"label":"蒙牛_低脂高钙牛奶海外版*航天版*_双码_可变多码关联","color":"#4e2daf"},{"label":"天水华盛_珀菲科特生榨玉米汁_底标码","color":"#395cc8"},{"label":"成都冠宇_滋升好多草莓风味饮料_角标码","color":"#ee6be2"},{"label":"宁夏夏进_益酸乳乳味饮料-草莓味_底标码","color":"#df8aad"},{"label":"维维_豆奶苗条马上白拿_可变码","color":"#eae139"},{"label":"蒙牛未来星骨力型*迪士尼版*_可变码","color":"#494262"},{"label":"四川沁养_阿莎姆果仁核桃饮品_可变码","color":"#f55988"},{"label":"保山瑞泽_保山瑞泽益慧仁核桃乳_可变码","color":"#bbb317"},{"label":"四川沁养_澳洲燕麦牛奶_可变码","color":"#a596b6"},{"label":"蒙牛纯牛奶海外版1L*航天版*_双码_可变多码关联","color":"#add949"},{"label":"四川奶小萌_恋日果园高钙中老年低糖低脂奶_角标码","color":"#c1c1af"},{"label":"山东伊怡_黑牛奶小盒码大福利_可变码","color":"#387cf4"},{"label":"纷美角标码","color":"#255c2f"},{"label":"四川雪域_雪域真情草莓果奶_角标码","color":"#ee9fe4"},{"label":"四川奶小萌_旺子高钙核桃花生奶_角标码","color":"#ac7c2d"},{"label":"汇源禹城_汇源红颜红豆饮料_角标码","color":"#83cd8f"},{"label":"宝灌来_养知堂中老年石磨核桃_角标码","color":"#981f7a"},{"label":"化州橘红_凉茶饮料","color":"#8db127"},{"label":"广美香满楼_广美香满楼红枣枸杞牛奶饮品","color":"#38f01f"},{"label":"纷美包装国际展会冠包试机品（英文俚语）_可变图","color":"#e2b8e2"},{"label":"四川元明_鑫元明高钙核桃花生奶_角标码","color":"#cd60d0"},{"label":"蒙牛低脂高钙牛奶海外版1L*航天版*_双码_可变多码关联","color":"#722859"},{"label":"四川奶小萌_喜响高钙核桃花生奶_角标码","color":"#26f26b"},{"label":"维维_维维豆奶盒码_可变码","color":"#957bea"},{"label":"成都冠宇_卓旺中老年核桃花生奶_角标码","color":"#74ebfb"},{"label":"怡元康_怡元康果蔬优果乳草莓味_可变码","color":"#221ed5"},{"label":"四川沁养阿莎姆果仁核桃饮品","color":"#2d9ec0"},{"label":"山东牛太太_中老年核桃牛奶-可变码","color":"#ff7c83"},{"label":"青岛特仑牧业_圣合碳烧酸奶_可变图","color":"#7eddc4"},{"label":"蒙牛_未来星成长有机奶*寻亲版*_可变码","color":"#9ac527"},{"label":"成都冠宇_蓉城家人高钙核桃花生奶_角标码","color":"#800298"},{"label":"维维天山雪","color":"#b1859c"},{"label":"成都冠宇蓉城家人东北大豆醇香原味豆奶_角标码","color":"#a2b38b"},{"label":"成都冠宇_成都冠宇蓉城家人高钙核桃早餐奶_角标码","color":"#884139"},{"label":"四川雪域_雪域真情贵缘核桃花生奶_角标码","color":"#91d9f4"},{"label":"四川奶小萌_喜响高钙核桃花生奶","color":"#e3a7da"},{"label":"怡元康_怡元康果蔬优果乳原味_可变码","color":"#163210"},{"label":"四川奶小萌_恋日果园高钙核桃花生奶_角标码","color":"#763bfc"},{"label":"成都冠宇_蓉城家人猴菇养生奶_角标码","color":"#987edd"},{"label":"成都冠宇_福仁缘枇杷原浆饮料_角标码","color":"#ba5548"},{"label":"成都冠宇_蓉城家人东北大豆香蕉豆奶_角标码","color":"#23156e"},{"label":"蒙牛_精选牧场纯牛奶_可变码","color":"#381a19"},{"label":"蒙牛_精选牧场纯牛奶改FSC_可变码","color":"#5decd4"},{"label":"新希望琴牌_新希望琴牌致轻纯牛奶_角标码","color":"#1d2455"},{"label":"重庆光大_重庆光大欧标牧场纯牛奶_底标码","color":"#6e25a0"},{"label":"纷美包装国际展会1000S试机品（国际景点）_可变图码","color":"#73afa6"},{"label":"天水长城_爱生活果汁饮料_角标码","color":"#5820ee"},{"label":"成都冠宇_蓉城家人柠檬柚子茶_角标码","color":"#5b9cab"},{"label":"上海沁爽_本豆本纯豆奶盒码_可变码","color":"#9c0042"},{"label":"蒙牛_低脂高钙牛奶_港澳版*可变印刷湖人*","color":"#744e90"},{"label":"成都冠宇_桃源农庄高钙核桃花生奶标准_角标码","color":"#c05819"},{"label":"福州健氏_澳牛高钙奶_底标码","color":"#992cd4"},{"label":"蒙牛纯牛奶海外版*航天版*_双码_可变多码关联","color":"#a3eb13"},{"label":"宁夏夏进_2017版纯牛奶_底标码","color":"#cd4ec3"},{"label":"金华好源_金华好源核桃牛奶马上白拿_可变多码关联","color":"#8389af"},{"label":"德玉泉_德玉泉红枣枸杞奶_角标码","color":"#7049ce"},{"label":"三元_智巧儿童成长牛奶（唐诗）_可变图码","color":"#71056a"},{"label":"临沂格瑞_益膳房学生奶甜橙味","color":"#e1cbde"},{"label":"成都冠宇_中社旭日红糖核桃花生奶标砖（黄色）_角标码","color":"#a00645"},{"label":"银川东君_贺兰牧场浓缩牛奶_底标码","color":"#5f5153"},{"label":"蒙牛_纯牛奶_港澳版*可变图码鹈鹕*","color":"#394903"},{"label":"蒙牛精选牧场纯牛奶","color":"#402869"},{"label":"新希望琴牌_新希望琴牌致轻低脂纯牛奶_角标码","color":"#d48789"},{"label":"三元_倍固儿童成长牛奶（唐诗）_可变图码","color":"#63d1bb"},{"label":"怡元康_怡元康豆比豆豆奶_可变图码","color":"#458605"},{"label":"四川奶小萌_恋日果园高钙核桃花生奶_角标码（固定码）","color":"#2e1bb2"},{"label":"蒙牛_蒙牛低脂高钙牛奶_港澳版*可变图码步行者*","color":"#354b9e"},{"label":"新希望阳平_新希望阳平特浓牛奶_角标码","color":"#ba259d"},{"label":"四川雪域_雪域真情原味果奶_角标码","color":"#6b4e00"},{"label":"四川奶小萌_伦苏牧场高钙低糖低脂牛奶_角标码","color":"#f4c29d"},{"label":"新希望阳平_新希望阳平高钙牛奶_角标码","color":"#d539f0"},{"label":"纷美包装国际展会200S试机品（国际景点）_可变图码","color":"#192cfc"},{"label":"新希望天香_新希望天香优酪乳_可变码","color":"#1cb6a6"},{"label":"山东卓尔兔巴哥","color":"#353545"},{"label":"四川奶小萌_旺鹫高钙核桃花生奶_角标码","color":"#c181e6"},{"label":"四川雪域_雪域真情酸奶风味乳酸菌_角标码","color":"#58fbc1"},{"label":"成都冠宇_桃源农庄钙锌核桃花生牛奶_角标码","color":"#a4ea60"},{"label":"广东正参_罗汉果菊花饮料_可变码","color":"#e08f91"},{"label":"纷美贸易_可变码测试","color":"#62888c"},{"label":"福建杂粮世家_核桃浓浆_角标码","color":"#c1a5e8"},{"label":"成都冠宇_蓉城家人苹果醋_角标码","color":"#f616d0"},{"label":"御膳香_御膳香顶羊纯羊奶苗条_角标码","color":"#9554c3"},{"label":"重庆光大_重庆光大豆之味调制豆乳_底标码","color":"#3f5e28"},{"label":"宁夏夏进_益酸乳乳味饮料-原味_底标码","color":"#1de105"},{"label":"三元_全护儿童成长牛奶（唐诗）_一包一码","color":"#4bd444"},{"label":"四川奶小萌_伦苏牧场中老年高钙低糖低脂奶_角标码","color":"#429759"},{"label":"重庆光大_重庆光大木瓜小镇_底标码","color":"#1a13a8"},{"label":"蒙牛_纯牛奶_港澳版*可变图码奇才*","color":"#936094"},{"label":"四川奶小萌_恋日果园高钙核桃花生奶（黄版）_角标码","color":"#63f08a"},{"label":"四川菊乐_四川菊乐酸乐奶21周年纪念版_角标码","color":"#4c088b"},{"label":"广美香满楼_纯牛奶_角标码","color":"#83423c"},{"label":"宁夏夏进_浓缩牛奶_底标码","color":"#15aa5a"},{"label":"纷美包装国际展会金属钻试机品（英文字母）_可变图","color":"#4b2a88"},{"label":"四川沁养澳洲燕麦牛奶","color":"#a8a7ce"},{"label":"成都冠宇_成都冠宇蓉城家人草莓乳味饮料_角标码","color":"#d8adda"},{"label":"四川元明_鑫元明酸乐奶_角标码","color":"#d2d99c"},{"label":"四川沁养菲希塔希腊风味酸奶","color":"#7f7218"},{"label":"宁夏夏进_2017年版浓缩纯牛奶_底标码","color":"#79031e"},{"label":"成都冠宇_云崖牧歌高钙核桃花生奶标准","color":"#1a0b8b"},{"label":"怡元康_达利致醇希腊酸奶马上白拿_可变码","color":"#6644dc"},{"label":"宜昌永和_永和豆奶（黑豆）","color":"#98077a"},{"label":"成都冠宇_桃源农庄高钙花生牛奶_角标码","color":"#288a8b"},{"label":"测试_隐藏码测试","color":"#82412b"},{"label":"成都冠宇_成都冠宇酸梅汤_角标码","color":"#190384"},{"label":"yyy_eee","color":"#78ed0d"},{"label":"成都冠宇_卓旺高钙核桃花生奶（优质）_角标码","color":"#d93eb6"},{"label":"数码通_图码关联","color":"#82203e"},{"label":"山东伊怡_甑酸奶黄桃味盒码_可变码","color":"#8e866c"},{"label":"蒙牛_特仑苏有机纯牛奶_可变图","color":"#22a0e1"},{"label":"重庆光大_重庆光大果蔬小镇_底标码","color":"#6f2cfd"},{"label":"成都冠宇_桃源农庄高钙核桃早餐奶_角标码","color":"#26b65d"},{"label":"怡元康豆士豆豆奶马上白拿_可变码","color":"#e71616"},{"label":"怡元康_福州达利园嘉然新西兰经典牧场马上白拿_可变码","color":"#a2a289"},{"label":"山东伊怡甑酸奶","color":"#f330f0"},{"label":"宝灌来太子奶新西兰牧场奶","color":"#dabc80"},{"label":"纷美贸易_纷美质量码 测试-05","color":"#371a6e"},{"label":"蒙牛_纯牛奶_港澳版*可变印刷雷霆*","color":"#6f57ff"},{"label":"福州健氏_澳牛纯牛奶_底标码","color":"#33eb7b"},{"label":"宝灌来_太子奶核桃花生奶苗条_可变码","color":"#db6448"},{"label":"宁夏夏进_塞上牧场纯牛奶（拼版)_一包一码","color":"#bfb9ba"},{"label":"四川奶小萌_旺子高钙中老年核桃花生奶_角标码","color":"#a929f3"},{"label":"纷美（北京）贸易_可变图码 流程测试","color":"#764f2b"},{"label":"成都冠宇_成都冠宇蓉城家人红版核桃花生奶_角标码","color":"#3d6814"},{"label":"成都冠宇_卓旺高钙核桃花生奶_角标码","color":"#a8230a"},{"label":"成都冠宇_蓉城家人核桃花生蛋白_角标码","color":"#534ba0"},{"label":"成都冠宇_蜀罐高钙核桃花生奶_角标码","color":"#4fb1c0"},{"label":"宝灌来_宝灌来乃之尊高钙核桃花生奶_角标码","color":"#862d2c"},{"label":"四川雪域_雪域真情花生核桃复合蛋白饮品_角标码","color":"#ccc6ad"},{"label":"维维_天山雪发酵原味酸乳酸菌马上白拿_可变码","color":"#ab990e"},{"label":"维维_豆奶标准马上白拿_可变码","color":"#25c8bd"},{"label":"成都冠宇_锅把火凉茶植物饮料_角标码","color":"#cb0fb9"},{"label":"河南舞阳益源_豆奶_时光豆留_可变码","color":"#e0a5ca"},{"label":"威海嘉盛_克莱斯姆纯牛奶码力全开_可变图码","color":"#ea4ee0"},{"label":"蒙牛_精选牧场纯牛奶世界杯版_可变码","color":"#b4c976"},{"label":"成都冠宇_上威早餐奶_角标码","color":"#8e9049"},{"label":"成都冠宇_都喜欢高钙核桃花生奶_角标码","color":"#cd4f8c"},{"label":"威海嘉盛_早餐奶_可变图","color":"#f3f3f7"},{"label":"威海嘉盛_红牛奶_可变图","color":"#7e9643"},{"label":"成都冠宇_上威中老年高钙核桃花生奶_角标码","color":"#6f46bd"},{"label":"成都冠宇_滋升中老年高钙低糖核桃花生奶_角标码","color":"#f420ae"},{"label":"成都冠宇_银禄星高钙核桃花生奶_角标码","color":"#1c26d7"},{"label":"云南来思尔_云南来思尔甜牛奶_马上白拿_可变多码关联","color":"#111b49"},{"label":"云南来思尔_云南来思尔纯牛奶_马上白拿_可变多码关联","color":"#63fb1c"},{"label":"重庆光大_重庆光大纯牛奶（蓝色）_底标码","color":"#ae0680"},{"label":"山东伊怡_100%纯牛奶苗条马上白拿_可变多码关联","color":"#625317"},{"label":"兔巴哥_兔巴哥酸奶马上白拿_可变码","color":"#1df120"},{"label":"北京贸易_200s白包加可变图和可变码","color":"#340ae4"},{"label":"厦门同顺_乐珍菊花饮料（2018促销版）马上白拿_可变码","color":"#6dcf2e"},{"label":"厦门同顺_菊花饮料（2018促销版）马上白拿_可变码","color":"#9406cc"},{"label":"厦门同顺_冬瓜茶果蔬味饮料（2018促销版）马上白拿_可变码","color":"#7136e0"},{"label":"厦门同顺_荔枝饮料（2018促销版）马上白拿_可变码","color":"#5b6a04"},{"label":"四川旺鹭_旺仔高钙核桃牛奶_马上白拿","color":"#4cf001"},{"label":"四川旺鹭_旺仔高钙花生核桃乳_马上白拿","color":"#3182da"},{"label":"蒙牛_蒙牛新养道零乳糖低脂电商*世界杯版*_可变图","color":"#6bc2ef"},{"label":"蒙牛_低脂高钙牛奶海外版1L*世界杯*_双码_可变多码关联","color":"#8c8470"},{"label":"蒙牛_纯牛奶海外版1L*世界杯*_双码_可变多码关联","color":"#62c1ee"},{"label":"蒙牛_低脂高钙牛奶海外版*世界杯*_双码_可变多码关联","color":"#3dd130"},{"label":"蒙牛_纯牛奶海外版*世界杯*_双码_可变多码关联","color":"#159048"},{"label":"四川旺鹭_旺仔中老年核桃花生牛奶_马上白拿_可变码","color":"#5a25d1"},{"label":"四川旺鹭_旺仔椰子牛乳复合蛋白饮料_马上白拿_可变码","color":"#e236b0"},{"label":"宁夏夏进_宁夏夏进塞上牧场纯牛奶（拼版)_可变图","color":"#78d596"}],"PieChart_Used":[{"label":"四川菊乐_四川菊乐酸乐奶21周年纪念版_角标码","color":"#4c088b","data":[189000756]},{"label":"新希望阳平_新希望阳平纯牛奶_角标码","color":"#9cd7ef","data":[71600256]},{"label":"蒙牛未来星","color":"#f13dc0","data":[47062464]},{"label":"新希望阳平_新希望阳平核桃花生奶（新版）_角标码","color":"#954c16","data":[46425150]},{"label":"宁夏夏进_益酸乳乳味饮料-草莓味_底标码","color":"#df8aad","data":[41440195]},{"label":"蒙牛_精选牧场纯牛奶_可变码","color":"#381a19","data":[39605184]},{"label":"宁夏夏进_益酸乳乳味饮料-原味_底标码","color":"#1de105","data":[28000152]},{"label":"蒙牛未来星佳智型*迪士尼版*_可变码","color":"#599b06","data":[26375118]},{"label":"蒙牛未来星骨力型*迪士尼版*_可变码","color":"#494262","data":[22830087]},{"label":"宁夏夏进_2017版纯牛奶_底标码","color":"#cd4ec3","data":[21720114]},{"label":"福州健氏_澳牛纯牛奶_底标码","color":"#33eb7b","data":[18800064]},{"label":"四川菊乐_酸乐奶21周年纪念版_角标码","color":"#cd9c9f","data":[16000020]},{"label":"宁夏夏进_益酸乳乳味饮料-菠萝味_底标码","color":"#cd9660","data":[13720087]},{"label":"蒙牛_未来星骨力型迪士尼版_可变码","color":"#8a25c0","data":[12650043]},{"label":"蒙牛_未来星佳智型迪士尼版_可变码","color":"#f6e810","data":[12498087]},{"label":"宁夏夏进_益酸乳乳味饮料-红枣味_底标码","color":"#8a10ac","data":[11740087]},{"label":"蒙牛_精选牧场纯牛奶世界杯版_可变码","color":"#b4c976","data":[11200050]},{"label":"福州健氏_澳牛高钙奶_底标码","color":"#992cd4","data":[11050074]},{"label":"新希望阳平_新希望阳平特浓牛奶_角标码","color":"#ba259d","data":[10690092]},{"label":"重庆光大_重庆光大娟姗王纯牛奶_底标码","color":"#e201e9","data":[8660088]},{"label":"蒙牛_未来星成长牛奶*歌声的翅膀*-200S_可变码","color":"#9a9d28","data":[8040018]},{"label":"蒙牛_精选牧场纯牛奶改FSC_可变码","color":"#5decd4","data":[7080066]},{"label":"新希望阳平_新希望阳平高钙牛奶_角标码","color":"#d539f0","data":[6350040]},{"label":"新希望雪兰_新希望雪兰易聪型儿童成长牛奶_可变图码","color":"#4d67d5","data":[6306300]},{"label":"新希望雪兰_新希望雪兰骨优型儿童成长牛奶_可变图码","color":"#8ace99","data":[6156150]},{"label":"成都冠宇_桃源农庄高钙核桃花生奶标准_角标码","color":"#c05819","data":[6150024]},{"label":"厦门同顺_冬瓜茶果蔬味饮料（2018促销版）马上白拿_可变码","color":"#7136e0","data":[5600016]},{"label":"维维_豆奶苗条马上白拿_可变码","color":"#eae139","data":[5500008]},{"label":"御膳香_御膳香顶羊纯羊奶苗条_角标码","color":"#9554c3","data":[5200092]},{"label":"新希望蝶泉_新希望蝶泉红枣牛奶_角标码","color":"#57cce7","data":[4830120]},{"label":"宁夏夏进_2017年版浓缩纯牛奶_底标码","color":"#79031e","data":[4760046]},{"label":"成都冠宇_蓉城家人高钙核桃花生奶_角标码","color":"#800298","data":[4700070]},{"label":"四川菊乐_四川菊乐酸乐奶21周年纪念版_角标码","color":"#4c088b","data":[4350024]},{"label":"维维_天山雪发酵原味酸乳酸菌马上白拿_可变码","color":"#ab990e","data":[4300002]},{"label":"新希望琴牌_新希望琴牌致轻纯牛奶_角标码","color":"#1d2455","data":[4230090]},{"label":"成都冠宇_蓉城家人东北大豆香蕉豆奶_角标码","color":"#23156e","data":[4200084]},{"label":"纷美角标码","color":"#255c2f","data":[3960144]},{"label":"新希望琴牌_新希望琴牌致轻低脂纯牛奶_角标码","color":"#d48789","data":[3900096]},{"label":"蒙牛白奶","color":"#f8bd74","data":[3772283]},{"label":"维维_维维豆奶盒码_可变码","color":"#957bea","data":[3500046]},{"label":"宁夏夏进_塞上牧场纯牛奶（拼版)_一包一码","color":"#bfb9ba","data":[3457080]},{"label":"三元儿童奶","color":"#cc3998","data":[3217338]},{"label":"完达慕容高钙核桃牛奶_角标码","color":"#dc7764","data":[3150072]},{"label":"成都冠宇_蓉城家人核桃花生蛋白_角标码","color":"#534ba0","data":[3150054]},{"label":"成都冠宇桃源农庄高钙核桃花生奶苗条_角标码","color":"#10dd4a","data":[3100032]},{"label":"成都冠宇_成都冠宇蓉城家人高钙核桃早餐奶_角标码","color":"#884139","data":[3030066]},{"label":"成都冠宇蓉城家人东北大豆醇香原味豆奶_角标码","color":"#a2b38b","data":[3000060]},{"label":"成都冠宇_云崖牧歌高钙核桃花生奶标准","color":"#1a0b8b","data":[3000060]},{"label":"天水华盛_珀菲科特野生沙棘汁_底标码","color":"#80b707","data":[3000024]},{"label":"重庆光大_重庆光大欧标牧场纯牛奶_底标码","color":"#6e25a0","data":[2820060]},{"label":"夏进塞上牧场纯牛奶","color":"#9aecdb","data":[2686518]},{"label":"重庆光大_重庆光大果蔬小镇_底标码","color":"#6f2cfd","data":[2550060]},{"label":"成都冠宇_蓉城家人猴菇养生奶_角标码","color":"#987edd","data":[2400048]},{"label":"天水华盛_珀菲科特核桃露_底标码","color":"#72e729","data":[2400012]},{"label":"厦门同顺_乐珍菊花饮料（2018促销版）马上白拿_可变码","color":"#6dcf2e","data":[2300004]},{"label":"厦门同顺_菊花饮料（2018促销版）马上白拿_可变码","color":"#9406cc","data":[2300004]},{"label":"维维_豆奶标准马上白拿_可变码","color":"#25c8bd","data":[2300004]},{"label":"成都冠宇_桃源农庄钙锌核桃花生牛奶_角标码","color":"#a4ea60","data":[2250036]},{"label":"云南来思尔_云南来思尔纯牛奶_马上白拿_可变多码关联","color":"#63fb1c","data":[2250000]},{"label":"怡元康_达利致醇希腊酸奶马上白拿_可变码","color":"#6644dc","data":[2100042]},{"label":"重庆光大_重庆光大欧标牧场高钙低脂牛奶_底标码","color":"#e66856","data":[1950048]},{"label":"四川雪域_雪域真情花生核桃复合蛋白饮品_角标码","color":"#ccc6ad","data":[1950030]},{"label":"成都冠宇_桃源农庄高钙花生牛奶_角标码","color":"#288a8b","data":[1950030]},{"label":"成都冠宇_成都冠宇蓉城家人红版核桃花生奶_角标码","color":"#3d6814","data":[1950030]},{"label":"成都冠宇_桃源农庄高钙低脂中老年核桃牛奶_角标码","color":"#b39c0c","data":[1950030]},{"label":"三元_倍固儿童成长牛奶（唐诗）_可变图码","color":"#63d1bb","data":[1801800]},{"label":"河北初元_太子草莓果味饮品盒码_可变码","color":"#721b2e","data":[1800055]},{"label":"重庆光大_重庆光大纯牛奶（蓝色）_底标码","color":"#ae0680","data":[1800054]},{"label":"怡元康_达利致醇新西兰牧场马上白拿_可变码","color":"#df0625","data":[1800036]},{"label":"重庆光大_重庆光大核桃花生奶_底标码","color":"#5667a6","data":[1800036]},{"label":"成都冠宇_成都冠宇蓉城家人草莓乳味饮料_角标码","color":"#d8adda","data":[1800036]},{"label":"成都冠宇_卓旺高钙核桃花生奶_角标码","color":"#a8230a","data":[1800036]},{"label":"厦门同顺_荔枝饮料（2018促销版）马上白拿_可变码","color":"#5b6a04","data":[1800000]},{"label":"山东牛太太中老年核桃牛奶","color":"#98f1a4","data":[1684999]},{"label":"金华好源_金华好源核桃牛奶马上白拿_可变多码关联","color":"#8389af","data":[1650024]},{"label":"重庆光大_重庆光大皇冠纯牛奶_底标码","color":"#65dcd7","data":[1590030]},{"label":"宁夏夏进_浓缩牛奶_底标码","color":"#15aa5a","data":[1560024]},{"label":"山东伊怡_黑牛奶小盒码大福利_可变码","color":"#387cf4","data":[1500030]},{"label":"云南来思尔_云南来思尔甜牛奶_马上白拿_可变多码关联","color":"#111b49","data":[1500012]},{"label":"四川沁养阿莎姆果仁核桃饮品","color":"#2d9ec0","data":[1450018]},{"label":"四川沁养澳洲燕麦牛奶","color":"#a8a7ce","data":[1450018]},{"label":"四川沁养菲希塔希腊风味酸奶","color":"#7f7218","data":[1450018]},{"label":"三元_智巧儿童成长牛奶（唐诗）_可变图码","color":"#71056a","data":[1351350]},{"label":"三元_倍固儿童成长牛奶（唐诗）_一包一码","color":"#4c6167","data":[1351350]},{"label":"临沂格瑞_益膳房学生纯牛奶扫码学唐诗_可变图码","color":"#a0b3d0","data":[1201200]},{"label":"三元_智巧儿童成长牛奶（唐诗）_可变图码","color":"#71056a","data":[1201200]},{"label":"保山瑞泽_保山瑞泽益慧仁核桃乳_可变码","color":"#bbb317","data":[1200024]},{"label":"成都冠宇_蓉城家人高钙核桃奶苗条_角标码","color":"#492dd0","data":[1200024]},{"label":"成都冠宇_蓉城家人苹果醋_角标码","color":"#f616d0","data":[1200024]},{"label":"成都冠宇_卓旺高钙核桃花生奶（优质）_角标码","color":"#d93eb6","data":[1200024]},{"label":"圣牧高科（天津）_熔岩烧酸奶饮品*改配料版*_可变码","color":"#ce2730","data":[1200024]},{"label":"成都冠宇_都喜欢高钙核桃花生奶_角标码","color":"#cd4f8c","data":[1200024]},{"label":"新希望琴牌_新希望琴牌致轻纯牛奶_角标码","color":"#1d2455","data":[1200024]},{"label":"成都冠宇_桃源农庄高钙核桃早餐奶_角标码","color":"#26b65d","data":[1200024]},{"label":"四川雪域_雪域真情贵缘核桃花生奶_角标码","color":"#91d9f4","data":[1200024]},{"label":"天水华盛_珀菲科特生榨玉米汁_底标码","color":"#395cc8","data":[1200006]},{"label":"蒙牛精选牧场纯牛奶","color":"#402869","data":[1170018]},{"label":"宝灌来太子奶核桃花生奶","color":"#3e8391","data":[1100000]},{"label":"怡元康_怡元康豆比豆豆奶_可变图码","color":"#458605","data":[1050624]},{"label":"重庆光大_重庆光大核桃花生奶_底标码","color":"#5667a6","data":[1050030]},{"label":"四川元明_鑫元明高钙核桃花生奶_角标码","color":"#cd60d0","data":[1050030]},{"label":"重庆光大_重庆光大豆之味调制豆乳_底标码","color":"#3f5e28","data":[1050030]},{"label":"四川元明_鑫元明酸乐奶_角标码","color":"#d2d99c","data":[1050030]},{"label":"怡元康豆士豆豆奶马上白拿_可变码","color":"#e71616","data":[1000026]},{"label":"成都冠宇_卓旺高钙核桃奶_角标码","color":"#ab6480","data":[950022]},{"label":"山东卓尔兔巴哥","color":"#353545","data":[950018]},{"label":"河北初元_太子红枣果味饮品盒码_可变码","color":"#744dbc","data":[900037]},{"label":"维维_维维豆奶盒码_可变码","color":"#957bea","data":[900036]},{"label":"成都冠宇_成都冠宇酸梅汤_角标码","color":"#190384","data":[900036]},{"label":"四川元明_鑫元明草莓味酸乐奶_角标码","color":"#b68612","data":[900036]},{"label":"宝灌来太子奶中老年奶","color":"#484295","data":[900036]},{"label":"四川草本_牧优高钙核桃花生牛奶_角标码","color":"#4b8143","data":[900036]},{"label":"重庆光大_重庆光大皇冠纯牛奶_底标码","color":"#65dcd7","data":[900018]},{"label":"山东伊怡甑酸奶","color":"#f330f0","data":[900018]},{"label":"成都冠宇_蜀罐黑芝麻珍品花生奶_角标码","color":"#6630ea","data":[900018]},{"label":"御膳香_顶羊纯山羊奶苗条_角标码","color":"#40d477","data":[900018]},{"label":"蒙牛_纯牛奶_港澳版*可变印刷雷霆*","color":"#6f57ff","data":[860058]},{"label":"威海嘉盛_克莱斯姆纯牛奶码力全开_可变图码","color":"#ea4ee0","data":[750141]},{"label":"四川旺鹭_旺仔中老年核桃花生牛奶_马上白拿_可变码","color":"#5a25d1","data":[750015]},{"label":"四川旺鹭_旺仔椰子牛乳复合蛋白饮料_马上白拿_可变码","color":"#e236b0","data":[750008]},{"label":"宝灌来_养知堂中老年石磨核桃_角标码","color":"#981f7a","data":[750006]},{"label":"四川旺鹭_旺仔高钙花生核桃乳_马上白拿","color":"#3182da","data":[750006]},{"label":"四川旺鹭_旺仔高钙核桃牛奶_马上白拿","color":"#4cf001","data":[750006]},{"label":"宝灌来_宝灌来乃之尊高钙核桃花生奶_角标码","color":"#862d2c","data":[750006]},{"label":"临沂格瑞_益膳房学生纯牛奶扫码学唐诗_可变图码","color":"#a0b3d0","data":[676200]},{"label":"上海沁爽_本豆本纯豆奶盒码_可变码","color":"#9c0042","data":[675024]},{"label":"蒙牛_纯牛奶_港澳版*可变图码森林狼*","color":"#5536e7","data":[655024]},{"label":"成都冠宇_银禄星高钙核桃花生奶_角标码","color":"#1c26d7","data":[600012]},{"label":"成都冠宇_滋升中老年高钙低糖核桃花生奶_角标码","color":"#f420ae","data":[600012]},{"label":"新希望天香_新希望天香优酪乳_可变码","color":"#1cb6a6","data":[600012]},{"label":"怡元康_福建达利园豆and豆豆奶马上白拿_可变码","color":"#5dbd7c","data":[600012]},{"label":"成都冠宇_蓉城家人柠檬柚子茶_角标码","color":"#5b9cab","data":[600012]},{"label":"河北初元_太子红枣果味饮品盒码（201708宁夏太子）_可变码","color":"#dced0b","data":[600012]},{"label":"怡元康_福州达利园嘉然新西兰经典牧场马上白拿_可变码","color":"#a2a289","data":[600012]},{"label":"四川雪域_雪域真情原味果奶_角标码","color":"#6b4e00","data":[600012]},{"label":"四川雪域_雪域真情酸奶风味乳酸菌_角标码","color":"#58fbc1","data":[600012]},{"label":"四川雪域_雪域真情草莓果奶_角标码","color":"#ee9fe4","data":[600012]},{"label":"河北初元_太子草莓果味饮品盒码（201708宁夏太子）_可变码","color":"#7766f2","data":[600012]},{"label":"成都冠宇_蜀罐高钙核桃花生奶_角标码","color":"#4fb1c0","data":[600012]},{"label":"成都冠宇_桃源农庄高钙花生牛奶_角标码","color":"#288a8b","data":[600012]},{"label":"宝灌来_太子奶雪域风情耗牛慕斯蓝莓味乳味饮品_角标码","color":"#eb15b5","data":[600012]},{"label":"成都冠宇_蜀罐黑芝麻珍品花生奶_角标码","color":"#6630ea","data":[600012]},{"label":"成都冠宇_锅把火凉茶植物饮料_角标码","color":"#cb0fb9","data":[600012]},{"label":"河南舞阳益源_豆奶_时光豆留_可变码","color":"#e0a5ca","data":[600012]},{"label":"兔巴哥_兔巴哥酸奶马上白拿_可变码","color":"#1df120","data":[600012]},{"label":"山东伊怡_100%纯牛奶苗条马上白拿_可变多码关联","color":"#625317","data":[600012]},{"label":"成都冠宇_蜀罐高钙核桃花生奶_角标码","color":"#4fb1c0","data":[600012]},{"label":"成都冠宇_上威早餐奶_角标码","color":"#8e9049","data":[600012]},{"label":"成都冠宇_上威中老年高钙核桃花生奶_角标码","color":"#6f46bd","data":[600012]},{"label":"蒙牛_低脂高钙牛奶_港澳版*可变印刷湖人*","color":"#744e90","data":[550044]},{"label":"圣牧高科（天津）熔岩烧酸奶饮品_可变码","color":"#88c290","data":[451521]},{"label":"成都冠宇_滋升好多草莓风味饮料_角标码","color":"#ee6be2","data":[450018]},{"label":"四川奶小萌_恋日果园高钙核桃花生奶_角标码","color":"#763bfc","data":[450018]},{"label":"成都冠宇_福仁缘枇杷原浆饮料_角标码","color":"#ba5548","data":[450018]},{"label":"四川奶小萌_喜响高钙核桃花生奶","color":"#e3a7da","data":[450018]},{"label":"云南乍甸_云南乍甸纯牛奶_角标码","color":"#4e8dff","data":[450018]},{"label":"怡元康_怡元康果蔬优果乳草莓味_可变码","color":"#221ed5","data":[450018]},{"label":"四川奶小萌_旺鹫高钙核桃花生奶_角标码","color":"#c181e6","data":[450018]},{"label":"怡元康_好彩头中老年高钙无蔗糖饮品_角标码","color":"#a5b63d","data":[450018]},{"label":"四川奶小萌_伦苏牧场高钙核桃花生奶_角标码","color":"#e93a98","data":[450018]},{"label":"宝灌来太子奶新西兰牧场奶","color":"#dabc80","data":[450018]},{"label":"成都冠宇爱啡客","color":"#f75576","data":[450018]},{"label":"四川奶小萌_伦苏牧场中老年高钙低糖低脂奶_角标码","color":"#429759","data":[450018]},{"label":"四川奶小萌_经旺高钙低糖核桃花生奶_角标码","color":"#a237f7","data":[450018]},{"label":"广东正参_罗汉果菊花饮料_可变码","color":"#e08f91","data":[450018]},{"label":"四川奶小萌_豪旺高钙核桃花生奶_角标码","color":"#1bb120","data":[450018]},{"label":"四川奶小萌_恋日果园高钙核桃花生奶（黄版）_角标码","color":"#63f08a","data":[450018]},{"label":"四川奶小萌_恋日果园高钙中老年低糖低脂奶_角标码","color":"#c1c1af","data":[450018]},{"label":"山东伊怡黑牛奶","color":"#3c9fb0","data":[450018]},{"label":"化州橘红_凉茶饮料","color":"#8db127","data":[450018]},{"label":"蒙牛_纯牛奶_港澳版*可变图码鹈鹕*","color":"#394903","data":[410024]},{"label":"蒙牛_纯牛奶_港澳版*可变图码奇才*","color":"#936094","data":[365024]},{"label":"成都冠宇_卓旺中老年核桃花生奶_角标码","color":"#74ebfb","data":[350010]},{"label":"数码通测试","color":"#ac8eb0","data":[330006]},{"label":"新希望天香_新希望天香香蕉牛奶_可变图码","color":"#adb9a3","data":[300006]},{"label":"蒙牛_纯牛奶海外版*世界杯*_双码_可变多码关联","color":"#159048","data":[300006]},{"label":"蒙牛_低脂高钙牛奶海外版*世界杯*_双码_可变多码关联","color":"#3dd130","data":[300006]},{"label":"蒙牛纯牛奶海外版*航天版*_双码_可变多码关联","color":"#a3eb13","data":[300006]},{"label":"北京贸易_200s白包加可变图和可变码","color":"#340ae4","data":[280140]},{"label":"蒙牛_低脂高钙牛奶海外版*航天版*_双码_可变多码关联","color":"#4e2daf","data":[200016]},{"label":"新希望天香_新希望天香香蕉牛奶熊猫TV混印_可变码","color":"#ef2e15","data":[200016]},{"label":"蒙牛_低脂高钙牛奶海外版1L*世界杯*_双码_可变多码关联","color":"#8c8470","data":[200000]},{"label":"蒙牛_纯牛奶海外版1L*世界杯*_双码_可变多码关联","color":"#62c1ee","data":[200000]},{"label":"测试白包_GAB250S隐藏折角码","color":"#c437a8","data":[160002]},{"label":"蒙牛低脂高钙牛奶海外版1L*航天版*_双码_可变多码关联","color":"#722859","data":[150000]},{"label":"蒙牛纯牛奶海外版1L*航天版*_双码_可变多码关联","color":"#add949","data":[150000]},{"label":"蒙牛_蒙牛低脂高钙牛奶_港澳版*可变图码步行者*","color":"#354b9e","data":[140008]},{"label":"测试_隐藏码测试","color":"#82412b","data":[140004]},{"label":"纷美包装国际展会200S试机品（国际景点）_可变图码","color":"#192cfc","data":[60060]},{"label":"yyy_eee","color":"#78ed0d","data":[60048]},{"label":"纷美包装国际展会1000S试机品（国际景点）_可变图码","color":"#73afa6","data":[40040]}],"PieChart_Avl":[{"label":"yyy_eee","color":"#78ed0d","data":[317512]}],"PieChart_Canned":[{"label":"酸酸乳","data":[737309330],"color":"#c6c10b"},{"label":"试机","data":[8541048],"color":"#2bbe17"},{"label":"三元儿童奶","data":[1916260],"color":"#cc3998"},{"label":"夏进塞上牧场纯牛奶","data":[781200],"color":"#9aecdb"}],"factoryAddress":{"_1A":{"code":"CNHHHT","name":"呼和浩特","latitude":40.82,"longitude":111.65},"_1R":{"code":"CNTA","name":"泰安","latitude":36.11,"longitude":117.08},"_4W":{"code":"CNDL","name":"大理","latitude":25.34,"longitude":100.13},"_1P":{"code":"CNTS","name":"唐山","latitude":39.36,"longitude":118.11},"_2P":{"code":"CNLN","name":"滦南","latitude":39.51,"longitude":118.68},"_2K":{"code":"CNQY","name":"清远","latitude":23.42,"longitude":113.01},"_2G":{"code":"CNMAS","name":"马鞍山","latitude":31.43,"longitude":118.28},"_2W":{"code":"CNMS","name":"眉山","latitude":29.36,"longitude":103.29},"_3K":{"code":"CNWH","name":"武汉","latitude":30.51,"longitude":114.31},"_4M":{"code":"CNTY","name":"太原","latitude":37.54,"longitude":112.33},"_1M":{"code":"CNJZ","name":"焦作","latitude":35.14,"longitude":113.12},"_2A":{"code":"CNGK","name":"高科","latitude":40.38,"longitude":111.83},"_5C":{"code":"CNSZ","name":"尚志","latitude":45.14,"longitude":127.55},"_4E":{"code":"CNCB","name":"察北","latitude":41.41,"longitude":114.95},"_3G":{"code":"CNJH","name":"金华","latitude":29.12,"longitude":119.64},"_3R":{"code":"CNHS","name":"衡水","latitude":37.71,"longitude":115.71},"_1T":{"code":"CNYC","name":"银川","latitude":38.47,"longitude":106.27},"_1Z":{"code":"CNWLMQ","name":"乌鲁木齐","latitude":43.77,"longitude":87.68},"_6G":{"code":"CNHEB","name":"哈尔滨","latitude":45.75,"longitude":126.63},"_BJ":{"code":"CNBJ","name":"北京","latitude":39.92,"longitude":116.46},"_S6":{"code":"CNS6","name":"石家庄","latitude":38.03,"longitude":114.26}},"PieChart_NewCanned":[{"label":"蒙牛_精选牧场纯牛奶_可变码","data":[28909400],"color":"#381a19"},{"label":"蒙牛_精选牧场纯牛奶改FSC_可变码","data":[5697600],"color":"#5decd4"},{"label":"蒙牛_精选牧场纯牛奶世界杯版_可变码","data":[4774600],"color":"#b4c976"},{"label":"蒙牛白奶","data":[1569100],"color":"#f8bd74"},{"label":"三元儿童奶","data":[1471800],"color":"#cc3998"},{"label":"蒙牛精选牧场纯牛奶","data":[1180900],"color":"#402869"},{"label":"蒙牛_纯牛奶_港澳版*可变印刷雷霆*","data":[448900],"color":"#6f57ff"},{"label":"蒙牛_低脂高钙牛奶_港澳版*可变印刷湖人*","data":[274700],"color":"#744e90"},{"label":"三元_倍固儿童成长牛奶（唐诗）_一包一码","data":[254700],"color":"#4c6167"},{"label":"蒙牛_纯牛奶_港澳版*可变图码森林狼*","data":[252200],"color":"#5536e7"},{"label":"蒙牛_纯牛奶_港澳版*可变图码鹈鹕*","data":[239100],"color":"#394903"},{"label":"三元_智巧儿童成长牛奶（唐诗）_可变图码","data":[192300],"color":"#71056a"},{"label":"蒙牛_纯牛奶_港澳版*可变图码奇才*","data":[149400],"color":"#936094"},{"label":"蒙牛纯牛奶海外版*航天版*_双码_可变多码关联","data":[106400],"color":"#a3eb13"},{"label":"蒙牛_纯牛奶海外版1L*世界杯*_双码_可变多码关联","data":[61400],"color":"#62c1ee"},{"label":"蒙牛_蒙牛低脂高钙牛奶_港澳版*可变图码步行者*","data":[59300],"color":"#354b9e"},{"label":"蒙牛_低脂高钙牛奶海外版1L*世界杯*_双码_可变多码关联","data":[36000],"color":"#8c8470"}]}